{
    "schema":{
        "$id": "https://freifunk.net/api-json-schema.json",
        "$schema": "https://json-schema.org/draft/2020-12/schema",
        "description": "Freifunk Community API X.X.X",
        "type": "object",
        "$defs": {
            "$comment": "Defining few fields to reuse in schema or subschema to improve modularity in the schema",

            "city": {
                "$id": "#city",
                "type": "string",
                "title": "City",
                "description": "Name of the city"
            },

            "country": {
                "$id": "#country",
                "type": "string",
                "title": "Country",
                "description": "Your conuntry, list has been taken from http://countrylist.net/de/",
                "enum": ["", "AF","AX","AL","DZ","AS","AD","AO","AI","AQ","AG","AR","AM","AW","AC","AU","AT","AZ","BS","BH","BD","BB","BY","BE","BZ","BJ","BM","BT","BO","BA","BW","BV","BR","IO","BN","BG","BF","BI","KH","CM","CA","IC","CV","KY","CF","TD","CL","CN","CX","CC","CO","KM","CG","CD","CK","CR","CI","HR","CU","CY","CZ","DK","DG","DJ","DM","DO","EC","EG","SV","GQ","ER","EE","ET","EU","FK","FO","FJ","FI","FR","GF","PF","TF","GA","GM","GE","DE","GH","GI","GR","GL","GD","GP","GU","GT","GG","GN","GW","GY","HT","HM","VA","HN","HK","HU","IS","IN","ID","IR","IQ","IE","IM","IL","IT","JM","JP","JE","JO","KZ","KE","KI","KP","KR","KW","KG","LA","LV","LB","LS","LR","LY","LI","LT","LU","MO","MK","MG","MW","MY","MV","ML","MT","MH","MQ","MR","MU","YT","MX","FM","MD","MC","MN","ME","MS","MA","MZ","MM","NA","NR","NP","NL","AN","NC","NZ","NI","NE","NG","NU","NF","MP","NO","OM","PK","PW","PS","PA","PG","PY","PE","PH","PN","PL","PT","PR","QA","RE","RO","RU","RW","SH","KN","LC","PM","VC","WS","SM","ST","SA","NT","SN","CS","SC","SL","SG","SK","SI","SB","SO","ZA","GS","SU","ES","LK","SD","SR","SJ","SZ","SE","CH","SY","TW","TJ","TZ","TH","TL","TG","TK","TO","TT","TA","TN","TR","TM","TC","TV","UG","UA","AE","GB","US","UY","UZ","VU","VE","VN","VG","VI","WF","EH","YE","ZM","ZW"]
            },

            "address": {
                "$id": "#address",
                "type":"object",
                "description": "The address of the place you meet",
                "properties": {
                    "name": {
                        "type": "string",
                        "title": "Name of your place",
                        "description": "The name of the place you meet"
                    },
                    "street": {
                        "type": "string",
                        "title": "Street",
                        "description": "The street address of your meeting place"
                    },
                    "zipcode": {
                        "type": "string",
                        "title": "ZIP",
                        "description": "The zip code of your meeting place"
                    }
                }
            },

            "lat": {
                "$id": "#lat",
                "type": "string",
                "title": "Latitude",
                "description": "Lattitude of your city in decimal degrees"
            },

            "lon": {
                "$id": "#lon",
                "type": "string",
                "title": "Longitude",
                "description": "Longitude of your city in decimal degrees"
            },

            "location": {
                "$comment": "Add title and description while reffering",
                "$id": "#location",
                "type": "object",
                "properties": {
                    "city": { "$ref": "#city" },
                    "country": { "$ref": "#country" },
                    "address": { "$ref": "#address" },
                    "lat": { "$ref": "#lat" },
                    "lon": { "$ref": "#lon" }
                },
                "required": ["city", "lat", "lon" ]
            },

            "email": {
                "$comment": "While using email field add description to it",
                "$id": "#email",
                "type": "string",
                "title": "Email",
				"pattern": "^[A-Za-z0-9äöüÄÖUß_\\-\\.]+@[A-Za-z0-9äöüÄÖUß_\\-\\.]+\\.[A-Za-z]{2,}$"
            },

            "url": {
                "$comment": "While using url this property add title and description",
                "$id": "#url",
                "type": "string",
                "pattern": "^(http|https)://[A-Za-z0-9ÄÖÜäöüß\\-_\\./]+"
            },

            "phone": {
                "$comment": "Add description while using this",
                "$id": "#phone",
                "type": "string",
                "title": "Phone"
            }
        },
        
        "properties": {
            "api": {
                "type": "string",
                "title": "API",
                "description": "The Freifunk Community API version you use",
                "enum": ["0.1", "0.2.0", "0.2.1", "0.3.0", "0.3.1", "0.3.2", "0.4.0", "0.4.1", "0.4.2", "0.4.3", "0.4.4", "0.4.5", "0.4.6", "0.4.7", "0.4.8", "0.4.9", "0.4.10", "0.4.11", "0.4.12", "0.4.13", "0.4.14", "0.4.15", "0.4.16", "X.X.X"],
                "default": "X.X.X"
            },

            "name": {
                "type": "string",
                "title": "Name",
                "description": "The name of your community"
            },

            "metacommunity": {
                "type": "string",
                "title": "Metacommunity",
                "description": "The name of your metacommunity, if your local community belongs to a bigger one"
            },

            "location": {
                "allOf": [
                    { "$ref": "#location" },
                    { "title": "Primary Location" },
                    { "description": "Position data such as a postal address or geographic coordinates" },
                    { "properties": {
                        "additionalLocations": {
                            "type": "array",
                            "title": "Additional Locations",
                            "description": "Add some more locations where your community is active.",
                            "items": { "$ref": "#loaction" }
                        }
                    } }
                ]
            },

            "contact": {
                "type": "object",
                "minProperties": 1,
                "properties": {
                    "email": {
                        "allOf": [
                            { "$ref": "#email" },
                            {"description": "Email address to which other people can contact your community (user@domain.com)" }
                        ]
                    },
                    "facebook": {
                        "type": "string",
                        "title": "facebook",
                        "description": "URL to your community's facebook account (https://facebook.com/...)",
                        "pattern": "^(http|https)://([a-z\\-]*\\.|)facebook\\.com/[A-Za-z0-9ÄÖÜäöüß\\-_\\.]+"
                    },
                    "identica": {
                        "type": "string",
                        "title": "identica",
                        "description": "URL to your community's identica account (https://identi.ca/...)",
                        "pattern": "^(http|https)://([a-z\\-]*\\.|)identi\\.ca/[A-Za-z0-9ÄÖÜäöüß\\-_\\.]+"
                    },
                    "irc": {
                        "type":"string",
                        "title": "IRC",
                        "description": "Your community's ICR channel; starts with irc://",
                        "pattern": "^(irc|ircs)://.*"
                    },
                    "jabber": {
                        "type": "string",
                        "title": "Jabber",
                        "description": "A jabber account someone reads (account@jabberserver.tld)",
                        "pattern": "^[A-Za-z0-9äöüÄÖUß_\\-\\.]+@[A-Za-z0-9äöüÄÖUß_\\-\\.]+\\.[A-Za-z]{2,}(\\?join){0,1}$"
                    },
                    "ml": {
                        "type": "string",
                        "title": "Mailinglist",
                        "description": "The email address (user@domain.com) of your mailing list or a link to the mailinglist info page (http{s}://...)",
                        "pattern": "^([A-Za-z0-9äöüÄÖUß_\\-\\.]+@[A-Za-z0-9äöüÄÖUß_\\-\\.]+\\.[A-Za-z]{2,}|(http|https)://[A-Za-z0-9ÄÖÜäöüß\\-_\\./]+)$"
                    },
                    "googleplus": {
                        "type": "string",
                        "title": "Google+",
                        "description": "URL to your community's g+ account (https://plus.google.com/...)",
                        "pattern": "^(http|https)://plus\\.google\\.com/[A-Za-z0-9ÄÖÜäöüß\\+\\-\\./_]+"
                    },
                    "matrix": {
                        "type": "string",
                        "title": "Matrix",
                        "description": "URL to your community's matrix channel (https://matrix.to/#/!...)",
                        "pattern": "^https://matrix\\.to/#/!"
                    },
                    "twitter": {
                        "type": "string",
                        "title": "Twitter",
                        "description": "Your community's Twitter name (starts with @)",
                        "pattern": "^@[A-Za-z0-9_\\-]{1,15}"
                    },
                    "webform": {
                        "allOf": [
                            { "$ref": "#url" },
                            { "title": "Webform" },
                            { "description": "URL to your community's contact form (http{s}://...)" }
                        ]
                    },
                    "phone": {
                        "allOf": [
                            { "$ref": "#phone" },
                            { "description": "If your community has a phone number (e.g. +49 1234 567890 based on the E.123 notation)" }
                        ]
                    }   
                }
            },

            "url": {
                "allOf": [
                    { "$ref": "#url" },
                    { "title": "HomePage" },
                    { "description": "The main website (http{s}://...)" }
                ]
            },

            "timeline": {
                "type": "array",
                "description": "These are lifetime events something like date of birth (and rebirth :-) of your community or other important milestones",
                "items": {
                    "type": "object",
                    "properties": {
                        "description": {
                            "type": "string",
                            "title": "Description",
                            "description": "Description of your lifetime event"
                        },
                        "timestamp": {
                            "type": "string",
                            "title": "Timestamp",
                            "description": "ISO 8601 timestamp of the event's date (format yyyy-mm-dd)",
                            "pattern": "^([0-9]{4})(?:-?W([0-9]+)(?:-?([0-9]+)D?)?|(?:-([0-9]+))?-([0-9]+))(?:[T ]([0-9]+):([0-9]+)(?::([0-9]+)(?:\\.([0-9]+))?)?)?(?:Z(-?[0-9]*))?"
                        },
                        "url": {
                            "allOf": [
                                { "$ref": "#url" },
                                { "title": "URL" },
                                { "description": "URL to details of this timeline-element" }
                            ]
                        }
                    }
                }
            },

            "feeds": {
                "type": "array",
                "title": "Feeds",
                "description": "Feeds you provide your community",
                "items": {
                    "type": "object",
                    "properties": {
                        "name": {
                            "type": "string",
                            "title": "Feed name",
                            "description": "Name of the feed"
                        },
                        "category": {
                            "type": "string",
                            "title": "Feed category",
                            "description": "Category of the feed like blog entries, calendars, forum messages, wiki articles, ...",
                            "enum": ["blog", "forum", "ics", "podcast", "wiki", "others", ""],
                            "default": ""
                        },
                        "type": {
                            "type": "string",
                            "title": "Feed Type",
                            "description": "Type of the feed like RSS, Atom, XML"
                        },
                        "url": {
                            "allOf": [
                                { "$ref": "#url" },
                                { "title": "URL" },
                                { "description": "URL of the feed" }
                            ]
                        }
                    }
                }

            },

            "states": {
                "type": "object",
                "title": "States",
                "description": "A collection of status-related data. Actual open/closed status, icons, last change timestamp etc.",
                "properties": {
                    "nodes": {
                        "type": "integer",
                        "minimun": 0,
                        "title": "Active Nodes",
                        "description": "Number of active nodes. This field is predestined to be updated regularly, please see sample solutions for <a href=\"https://github.com/Freifunk-Mainz/changeffapi\" target=\"_blank\">Gluon</a> or <a href=\"https://github.com/freifunk/common.api.freifunk.net/blob/master/contrib/ffapi-update-nodes.py\" target=\"_blank\">OLSR</a>"
                    },
                    "lastchange": {
                        "type":"string",
                        "title": "Last Change",
                        "description": "At what ISO 8601 timestamp has your community status lastly changed?",
                        "default": 0
                    },
                    "message": {
                        "type": "string",
                        "title": "Message",
                        "description": "A free-form string something like 'open for public', 'members only' or whatever you want it to be)"
                    },
                    "description": {
                        "type":"string",
                        "title": "Description",
                        "description": "Describe your community in a few lines"
                    },
                    "focus": {
                        "type": "array",
                        "title": "Focus",
                        "description": "What's the focus of your local community?",
                        "items": {
                            "type": "string",
                            "title": "option",
                            "enum": ["infrastructure/backbone", "Public Free Wifi", "Social Community Building", "Local services and content", "Free internet access" ]
                        }
                    }
                },
                "required": [ "lastchange" ]
            },

            "nodeMaps": {
                "type": "array",
                "title": "Nodes",
                "description": "Maps of nodes or topology your community provides",
                "items": {
                    "type": "object",
                    "properties": {
                        "url": {
                            "allOf": [
                                { "$ref": "#url" },
                                { "title": "URL of the map" },
                                { "description": "The URL where the map is located" }
                            ]
                        },
                        "interval": {
                            "type": "string",
                            "title": "interval",
                            "description": "How often the map will be refreshed"
                        },
                        "technicalType": {
                            "type": "string",
                            "title": "map techincal type",
                            "description": "The kind of map is used",
                            "enum": [ "", "ffmap", "ffsomething", "olsr-dot", "openwifimap", "netmon", "libremap", "nodewatcher", "kml", "nodelist", "meshviewer", "hopglass" ],
                            "default": ""
                        },
                        "mapType": {
                            "type": "string",
                            "title": "",
                            "description": "",
                            "enum": [ "", "geographical", "structural", "list/status" ],
                            "default": ""
                        }
                    }
                }
            },
            "services": {
                "type": "array",
                "title": "Services",
                "description": "Services Provided by your community",
                "items": {
                    "type": "object",
                    "properties": {
                        "serviceName": {
                            "type": "string",
                            "title": "Service Name",
                            "description": "Name of your service (e.g. jabber...)"
                        },
                        "serviceDescription": {
                            "type": "string",
                            "title": "Service Description",
                            "description": "Describe your service"
                        },
                        "externalUri": {
                            "type": "string",
                            "title": "External URI",
                            "description": "URI to use your service from the internet"
                        },
                        "internalURI": {
                            "type": "string",
                            "title": "Internal URI",
                            "description": "URI to use your service from Freifunk or icvpn-networks"
                        }
                    }
                }
            },
            "support": {
                "type": "object",
                "title": "Support for your community",
                "properties": {
                    "club": {
                        "type": "object",
                        "title": "Supporting Club",
                        "properties": {
                            "name": {
                                "type": "string",
                                "title": "Club Name",
                                "description": "Name of the Club"
                            },
                            "street": {
                                "type": "string",
                                "title": "Street",
                                "description": "Address - Street"
                            },
                            "zip": {
                                "type": "string",
                                "title": "ZIP",
                                "description": "Address - ZIP"
                            },
                            "city": { "$ref": "#city" },
                            "url": {
                                "allOf": [
                                    { "$ref": "#url" },
                                    { "title": "HomePage" },
                                    { "description": "The club's website (http{s}://...)" }
                                ]
                            },
                            "email": {
                                "allOf": [
                                    { "$ref": "#email" },
                                    { "description": "Email address to contact the club (user@domain.com)" }
                                ]
                            },
                            "board": {
                                "type": "array",
                                "title": "Board Members",
                                "description": "Who are the board members of the club?",
                                "items": {
                                    "type": "string",
                                    "title": "Name"
                                }
                            }
                        }
                    }
                },
                "donations": {
                    "type": "object",
                    "title": "Donations",
                    "properties": {
                        "bankaccount": {
                            "type": "object",
                            "title": "Bank Account",
                            "properties": {
                                "IBAN": {
                                    "type": "string",
                                    "title": "IBAN"
                                },
                                "BIC": {
                                    "type": "string",
                                    "title": "BIC"
                                },
                                "usage": {
                                    "type": "string",
                                    "title": "Usage of the donations",
                                    "description": "Please use this string as transfer-purpose to define a special usage of your donation."
                                }
                            }
                        },
                        "campaigns": {
                            "type": "array",
                            "title": "Campaigns",
                            "items": {
                                "type": "object",
                                "properties": {
                                    "provider": {
                                        "type": "string",
                                        "title": "Campaign Providers",
                                        "description": "Where do you host your donations?",
                                        "enum": [ "", "betterplace", "boost" ],
                                        "default": ""
                                    },
                                    "projectid": {
                                        "type": "string",
                                        "title": "Project ID",
                                        "description": "ID of your project, Betterplace-IDs are multiple digits and can be found within the URL"
                                    }
                                }
                            }
                        }
                    }
                }
            },

            "socialprojects": {
                "type": "object",
                "title": "",
                "properties": {
                    "number": {
                        "type": "integer",
                        "mininum": 0,
                        "title": "Number of Projects",
                        "description": "Number of projects supported by your Community"
                    },
                    "website": {
                        "allOf": [
                            { "$ref": "#url" },
                            { "title": "URL of your page" },
                            { "description": "A link to a web site where people can find an overview over your projects" }
                        ]
                    },
                    "contact": {
                        "allOf": [
                            { "$ref": "#email" },
                            { "title": "Contact Email" },
                            { "description": "Please provide an email address to contact you on refugees and social projects" }
                        ]
                    }
                }
            },

            "privacy": {
                "type": "object",
                "title": "Privacy Policy",
                "properties": {
                    "policyurl": {
                        "allOf": [
                            { "$ref": "#url" },
                            { "title": "Privacy Policy URL" },
                            { "description": "URL to your privacy policy description" }
                        ]
                    }
                }
            }

        },
        "required": ["api", "name", "location", "contact", "url", "states" ],
        "additionalProperties": false
    }
}